{
    "family_name": "Osei",
    "move_in_date": "2023-10-11",
    "number_of_people": 5,
    "visited_by_bishopric": true,
    "family_members": [
      {
        "name": "Kwame Osei",
        "gender": "male",
        "birthdate": "1980-01-01"
      },
      {
        "name": "Afua Doe",
        "gender": "female",
        "birthdate": "1985-02-02"
      },
      {
        "name": "Kofi Osei",
        "gender": "male",
        "birthdate": "2005-03-03"
      },
      {
        "name": "Ama Osei",
        "gender": "female",
        "birthdate": "2007-04-04"
      },
      {
        "name": "Akosua Osei",
        "gender": "female",
        "birthdate": "2010-05-05"
      }
    ]
  }
  